hk_homepage/__init__.py
hk_homepage/router.py
hk_homepage/static/style.css
hk_homepage/templates/header.html
hk_homepage-0.1.0.dist-info/METADATA
hk_homepage-0.1.0.dist-info/RECORD
hk_homepage-0.1.0.dist-info/WHEEL
hk_homepage-0.1.0.dist-info/top_level.txt
test/__init__.py
