Metadata-Version: 2.1
Name: hk-homepage
Version: 0.1.0
Summary: Hermann Krumrey's personal home page
Home-page: https://gitlab.namibsun.net/namibsun/python/hk-homepage
Author: Hermann Krumrey
Author-email: hermann@krumreyh.com
License: GNU GPL3
Platform: UNKNOWN
Classifier: License :: OSI Approved :: GNU General Public License v3 (GPLv3)
Requires-Dist: flask
